README.rst
bender_hooks.py
setup.py
bender_hooks.egg-info/PKG-INFO
bender_hooks.egg-info/SOURCES.txt
bender_hooks.egg-info/dependency_links.txt
bender_hooks.egg-info/top_level.txt