Metadata-Version: 1.1
Name: bender-hooks
Version: 0.1.0
Summary: Create hooks as decorators.
Home-page: https://github.com/bender-bot/bender-hooks
Author: Fabio Menegazzo <menegazzo@gmail.com>, Bruno Oliveira <nicoddemus@gmail.com>
Author-email: UNKNOWN
License: LGPLv3
Keywords: hook,decorator,interface
Platform: UNKNOWN
Classifier: Development Status :: 2 - Pre-Alpha
Classifier: Intended Audience :: Developers
Classifier: License :: OSI Approved :: GNU Lesser General Public License v3 (LGPLv3)
Classifier: Programming Language :: Python :: 2.6
Classifier: Programming Language :: Python :: 2.7
Classifier: Programming Language :: Python :: 3.2
Classifier: Programming Language :: Python :: 3.3
Classifier: Programming Language :: Python :: 3.4
Classifier: Programming Language :: Python :: Implementation :: PyPy
